gpt_pydantic_tools/__init__.py
gpt_pydantic_tools-0.2.dist-info/LICENSE
gpt_pydantic_tools-0.2.dist-info/METADATA
gpt_pydantic_tools-0.2.dist-info/WHEEL
gpt_pydantic_tools-0.2.dist-info/top_level.txt
gpt_pydantic_tools-0.2.dist-info/RECORD
