Metadata-Version: 2.1
Name: gpt_pydantic_tools
Version: 0.2
Summary: Define GPT tool schemas using Pydantic.
Author-email: "Carlos A. Planchón" <carlosandresplanchonprestes@gmail.com>
License: MIT License
Project-URL: repository, https://github.com/carlosplanchon/gpt_pydantic_tools.git
Keywords: gpt,ai,tool,schemas,pydantic,json
Classifier: Intended Audience :: Developers
Classifier: Topic :: Software Development :: Build Tools
Classifier: License :: OSI Approved :: MIT License
Classifier: Programming Language :: Python :: 3.12
License-File: LICENSE
Requires-Dist: attrs >=23.2.0
Requires-Dist: attrs-strict >=1.0.1
Requires-Dist: pydantic >=2.7.1
Requires-Dist: jsonschema >=4.22.0
